<?xml version="1.0" encoding="utf-8"?>
<FacturaElectronica xmlns:ds="http://www.w3.org/2000/09/xmldsig#" xmlns:xsi="http://www.w3.org/2001/XMLSchema-instance" xmlns="https://cdn.comprobanteselectronicos.go.cr/xml-schemas/v4.3/facturaElectronica" xsi:schemaLocation="https://cdn.comprobanteselectronicos.go.cr/xml-schemas/v4.3/facturaElectronica https://cdn.comprobanteselectronicos.go.cr/xml-schemas/v4.3/facturaElectronica.xsd">
    <Clave>50609022200050385019700100002010000000018100000018</Clave>
    <CodigoActividad>722003</CodigoActividad>
    <NumeroConsecutivo>00100002010000000018</NumeroConsecutivo>
<FechaEmision>2022-02-09T14:57:38-06:00</FechaEmision>
    <Emisor>
<Nombre>Heriberto Castro Fernandez</Nombre>
<Identificacion>
<Tipo>01</Tipo>
<Numero>503850197</Numero>
</Identificacion>
<NombreComercial>Heriberto Castro Fernandez</NombreComercial>
<Ubicacion>
<Provincia>1</Provincia>
<Canton>18</Canton>
<Distrito>01</Distrito>
<Barrio>01</Barrio>
<OtrasSenas>Lomas de Ayarco</OtrasSenas>
</Ubicacion>
<Telefono>
<CodigoPais>506</CodigoPais>
<NumTelefono>86365851</NumTelefono>
</Telefono>
<CorreoElectronico>heri9109@gmail.com</CorreoElectronico>
    </Emisor>
    <Receptor>
<Nombre>dylan salazar salguero</Nombre>
<Identificacion>
<Tipo>01</Tipo>
<Numero>117460435</Numero>
</Identificacion>
<Ubicacion>
<Provincia>1</Provincia>
<Canton>18</Canton>
<Distrito>01</Distrito>
<OtrasSenas>LOCAL COMERCIAL</OtrasSenas>
</Ubicacion>
<Telefono>
<CodigoPais>506</CodigoPais>
<NumTelefono>11111111</NumTelefono>
</Telefono>
<CorreoElectronico>dsalazar@digitalsat-cr.com</CorreoElectronico>
 </Receptor>
  <CondicionVenta>01</CondicionVenta>
  <PlazoCredito>0</PlazoCredito>
  <MedioPago>01</MedioPago>
  <DetalleServicio>
   <LineaDetalle>
      <NumeroLinea>1</NumeroLinea>
      <Codigo>8314300000000</Codigo>
      <CodigoComercial>
      <Tipo>01</Tipo>
      <Codigo>2</Codigo>
      </CodigoComercial>
      <Cantidad>1</Cantidad>
      <UnidadMedida>Unid</UnidadMedida>
      <Detalle>Alquiler sistema administrativo</Detalle>
      <PrecioUnitario>200.00000</PrecioUnitario>
      <MontoTotal>200.00000</MontoTotal>
      <Descuento>
        <MontoDescuento>0.00000</MontoDescuento>
        <NaturalezaDescuento>Descuento</NaturalezaDescuento>
      </Descuento>
      <SubTotal>200.00000</SubTotal>
        <Impuesto>
        <Codigo>01</Codigo>
        <CodigoTarifa>08</CodigoTarifa>
        <Tarifa>13.00000</Tarifa>
        <Monto>26.00000</Monto>
        </Impuesto>
      <MontoTotalLinea>226.00000</MontoTotalLinea>
    </LineaDetalle>
  </DetalleServicio>
  <ResumenFactura>
    <CodigoTipoMoneda>
<CodigoMoneda>CRC</CodigoMoneda>
<TipoCambio>1.00000</TipoCambio>
</CodigoTipoMoneda>
    <TotalServGravados>0.00000</TotalServGravados>
    <TotalServExentos>0.00000</TotalServExentos>
    <TotalMercanciasGravadas>200.00000</TotalMercanciasGravadas>
    <TotalMercanciasExentas>0.00000</TotalMercanciasExentas>   
    <TotalGravado>200.00000</TotalGravado>
    <TotalExento>0.00000</TotalExento>
    <TotalVenta>200.00000</TotalVenta>
    <TotalDescuentos>0.00000</TotalDescuentos>
    <TotalVentaNeta>200.00000</TotalVentaNeta>
    <TotalImpuesto>26.00000</TotalImpuesto>
    <TotalComprobante>226.00000</TotalComprobante>
  </ResumenFactura></FacturaElectronica>
